boomerang/__init__.py
boomerang/buttons.py
boomerang/events.py
boomerang/exceptions.py
boomerang/messages.py
boomerang/server.py
boomerang-0.6.0.dist-info/DESCRIPTION.rst
boomerang-0.6.0.dist-info/METADATA
boomerang-0.6.0.dist-info/RECORD
boomerang-0.6.0.dist-info/WHEEL
boomerang-0.6.0.dist-info/metadata.json
boomerang-0.6.0.dist-info/top_level.txt
