Metadata-Version: 2.0
Name: boomerang
Version: 0.6.0
Summary: An asynchronous Python library for building services on the Facebook Messenger Platform
Home-page: https://github.com/kdelwat/boomerang
Author: Cadel Watson
Author-email: cadel@cadelwatson.com
License: MIT license
Keywords: boomerang
Platform: UNKNOWN
Classifier: Development Status :: 2 - Pre-Alpha
Classifier: Intended Audience :: Developers
Classifier: License :: OSI Approved :: MIT License
Classifier: Natural Language :: English
Classifier: Programming Language :: Python :: 3.5
Classifier: Programming Language :: Python :: 3.6
Requires-Dist: aiohttp
Requires-Dist: sanic
